README.md
setup.py
aiocrawler/__init__.py
aiocrawler/commands.py
aiocrawler/engine.py
aiocrawler/item.py
aiocrawler/job_scheduler.py
aiocrawler/log.py
aiocrawler/request.py
aiocrawler/response.py
aiocrawler/settings.py
aiocrawler/spider.py
aiocrawler.egg-info/PKG-INFO
aiocrawler.egg-info/SOURCES.txt
aiocrawler.egg-info/dependency_links.txt
aiocrawler.egg-info/entry_points.txt
aiocrawler.egg-info/requires.txt
aiocrawler.egg-info/top_level.txt
aiocrawler/dashboard/__init__.py
aiocrawler/dashboard/dashboard.py
aiocrawler/downloaders/__init__.py
aiocrawler/downloaders/aio_downloader.py
aiocrawler/downloaders/downloader.py
aiocrawler/extensions/__init__.py
aiocrawler/extensions/redis.py
aiocrawler/extensions/templates.py
aiocrawler/extensions/exporters/__init__.py
aiocrawler/extensions/exporters/exporter.py
aiocrawler/extensions/exporters/redis_exporter.py
aiocrawler/extensions/exporters/redis_to_file.py
aiocrawler/extensions/exporters/redis_to_mongo.py
aiocrawler/filters/__init__.py
aiocrawler/filters/filter.py
aiocrawler/filters/memory_filter.py
aiocrawler/filters/redis_filter.py
aiocrawler/middlewares/__init__.py
aiocrawler/middlewares/allowed_codes_middleware.py
aiocrawler/middlewares/middleware.py
aiocrawler/middlewares/proxy_middleware.py
aiocrawler/middlewares/set_default_middleware.py
aiocrawler/middlewares/user_agent_middleware.py
aiocrawler/schedulers/__init__.py
aiocrawler/schedulers/memory_scheduler.py
aiocrawler/schedulers/redis_scheduler.py
aiocrawler/schedulers/scheduler.py
aiocrawler/templates/__init__.py
aiocrawler/templates/items.tmpl
aiocrawler/templates/middlewares.tmpl
aiocrawler/templates/run.tmpl
aiocrawler/templates/settings.tmpl
aiocrawler/templates/spiders.tmpl