Metadata-Version: 1.1
Name: aiocrawler
Version: 1.22
Summary: The aiocrawler is a asynchronous/distributed web crawler/spider
Home-page: https://github.com/kylin1020/aiocrawler
Author: kylin1020
Author-email: kylin0521@gmail.com
License: MIT
Keywords: spider,asynchronous,crawler,distributed
Platform: UNKNOWN
Classifier: Environment :: Web Environment
Classifier: Topic :: Internet
Classifier: Topic :: Software Development :: Libraries :: Python Modules
Classifier: Programming Language :: Python
Classifier: Programming Language :: Python :: 3.6
Classifier: Programming Language :: Python :: 3.7
